MANIFEST.in
README.md
setup.py
./.env
./.gitignore
./BRANCH.txt
./Dockerfile
./MANIFEST.in
./README.md
./VERSION.txt
./cred_gcs.json
./loop_parallelism.py
./main_Femto.py
./main_coon.py
./main_esg.py
./main_federated.py
./main_imputation.py
./main_optimal_k.py
./main_sparsity.py
./make_docker.sh
./make_yaml.py
./requirements.txt
./root_path.py
./setup.py
./.git/FETCH_HEAD
./.git/HEAD
./.git/config
./.git/description
./.git/index
./.git/hooks/applypatch-msg.sample
./.git/hooks/commit-msg.sample
./.git/hooks/fsmonitor-watchman.sample
./.git/hooks/post-update.sample
./.git/hooks/pre-applypatch.sample
./.git/hooks/pre-commit.sample
./.git/hooks/pre-merge-commit.sample
./.git/hooks/pre-push.sample
./.git/hooks/pre-rebase.sample
./.git/hooks/pre-receive.sample
./.git/hooks/prepare-commit-msg.sample
./.git/hooks/push-to-checkout.sample
./.git/hooks/update.sample
./.git/info/exclude
./.git/logs/HEAD
./.git/logs/refs/heads/dev
./.git/logs/refs/remotes/origin/dev
./.git/logs/refs/remotes/origin/master
./.git/logs/refs/remotes/origin/pd.femto
./.git/logs/refs/remotes/origin/staging
./.git/objects/f7/7a645ebc896cc3a87dbda16e56817c5fd4b437
./.git/objects/pack/pack-aef61822942fde8af8a77a94bea27e5440e8b879.idx
./.git/objects/pack/pack-aef61822942fde8af8a77a94bea27e5440e8b879.pack
./.git/refs/heads/dev
./.git/refs/remotes/origin/dev
./.git/refs/remotes/origin/master
./.git/refs/remotes/origin/pd.femto
./.git/refs/remotes/origin/staging
./.git/refs/tags/v1.0
./.github/workflows/pull-request-staging.yml
./.github/workflows/pull-request.yml
./.github/workflows/push-dev.yml
./.github/workflows/push-staging.yml
./.github/workflows/push.yml
./adlinear/__init__.py
./adlinear/clusterizer.py
./adlinear/dask_tester.py
./adlinear/data_collector.py
./adlinear/features_selector.py
./adlinear/fed_nmtf.py
./adlinear/imputer.py
./adlinear/nmf_k_estimator.py
./adlinear/nmfmodel.py
./adlinear/ntfmodel.py
./adlinear/pca.py
./adlinear/testers.py
./adlinear/utilities.py
./adlinear_dev.egg-info/PKG-INFO
./adlinear_dev.egg-info/SOURCES.txt
./adlinear_dev.egg-info/dependency_links.txt
./adlinear_dev.egg-info/requires.txt
./adlinear_dev.egg-info/top_level.txt
adlinear_dev.egg-info/PKG-INFO
adlinear_dev.egg-info/SOURCES.txt
adlinear_dev.egg-info/dependency_links.txt
adlinear_dev.egg-info/requires.txt
adlinear_dev.egg-info/top_level.txt
